pyphaser/__init__.py
pyphaser/arcade/__init__.py
pyphaser/arcade/app.py
pyphaser/js/phaser.html
pyphaser/pg/__init__.py
pyphaser/pg/app.py
pyphaser/resources/bomb.png
pyphaser/resources/dude.png
pyphaser/resources/platform.png
pyphaser/resources/sky.png
pyphaser/resources/star.png
pyphaser-1.0.2.dist-info/METADATA
pyphaser-1.0.2.dist-info/WHEEL
pyphaser-1.0.2.dist-info/entry_points.txt
pyphaser-1.0.2.dist-info/RECORD
