Metadata-Version: 2.3
Name: pyphaser
Version: 1.0.2
Summary: 
Author: Ralph Brecheisen
Author-email: ralph.brecheisen@gmail.com
Requires-Python: >=3.11
Classifier: Programming Language :: Python :: 3
Classifier: Programming Language :: Python :: 3.11
Classifier: Programming Language :: Python :: 3.12
Classifier: Programming Language :: Python :: 3.13
Requires-Dist: arcade (>=3.3.2)
Requires-Dist: pygame (>=2.6.1)
